cognee_community_vector_adapter_redis/__init__.py
cognee_community_vector_adapter_redis/redis_adapter.py
cognee_community_vector_adapter_redis/register.py
cognee_community_vector_adapter_redis-0.0.3.dist-info/METADATA
cognee_community_vector_adapter_redis-0.0.3.dist-info/WHEEL
cognee_community_vector_adapter_redis-0.0.3.dist-info/RECORD
