Metadata-Version: 2.4
Name: cognee-community-vector-adapter-redis
Version: 0.0.3
Summary: Redis vector database adapter for cognee
Requires-Python: <=3.13,>=3.11
Requires-Dist: cognee>=0.2.0.dev0
Requires-Dist: redisvl<=1.0.0,>=0.6.0
